tests/__init__.py
tests/conftest.py
tests/test_orm.py
tests/test_zungle.py
zungle/__init__.py
zungle/api.py
zungle/middleware.py
zungle/orm.py
zungle/response.py
zungle-0.0.4.dist-info/METADATA
zungle-0.0.4.dist-info/WHEEL
zungle-0.0.4.dist-info/top_level.txt
zungle-0.0.4.dist-info/RECORD
